dftd3-1.2.1.dist-info/RECORD
dftd3-1.2.1.dist-info/WHEEL
dftd3-1.2.1.dist-info/METADATA
dftd3/_libdftd3.cpython-39-darwin.so
dftd3/test_library.py
dftd3/ase.py
dftd3/library.py
dftd3/test_ase.py
dftd3/interface.py
dftd3/__init__.py
dftd3/test_parameters.py
dftd3/pyscf.py
dftd3/test_qcschema.py
dftd3/parameters.toml
dftd3/parameters.py
dftd3/qcschema.py
dftd3/test_interface.py
dftd3/test_pyscf.py
dftd3/.dylibs/libgfortran.5.dylib
dftd3/.dylibs/libquadmath.0.dylib
dftd3/.dylibs/libgcc_s.1.1.dylib
dftd3-1.2.1.data/data/licenses/mctc-lib/jsonfortran/LICENSE
