Metadata-Version: 2.1
Name: dftd3
Version: 1.2.1
Summary: Python API of the DFT-D3 project
License: LGPL-3.0-or-later
Classifier: Intended Audience :: Science/Research
Classifier: Programming Language :: Fortran
Classifier: Programming Language :: Python :: 3
Classifier: Programming Language :: Python :: 3.7
Classifier: Programming Language :: Python :: 3.8
Classifier: Programming Language :: Python :: 3.9
Classifier: Programming Language :: Python :: 3.10
Classifier: Programming Language :: Python :: 3.11
Classifier: Programming Language :: Python :: 3.12
Classifier: Programming Language :: Python :: 3.13
Classifier: Topic :: Scientific/Engineering :: Chemistry
Classifier: Topic :: Scientific/Engineering :: Physics
Project-URL: repository, https://github.com/dftd3/simple-dftd3
Project-URL: documentation, https://dftd3.readthedocs.io
Requires-Python: >=3.7
Requires-Dist: cffi
Requires-Dist: numpy
Provides-Extra: ase
Requires-Dist: ase; extra == "ase"
Provides-Extra: qcschema
Requires-Dist: qcelemental; extra == "qcschema"
Provides-Extra: pyscf
Requires-Dist: pyscf; extra == "pyscf"
Provides-Extra: test
Requires-Dist: pytest; extra == "test"
Requires-Dist: pytest-cov; extra == "test"
